ajaxviews/__init__.py
ajaxviews/forms.py
ajaxviews/helpers.py
ajaxviews/mixins.py
ajaxviews/queries.py
ajaxviews/tests.py
ajaxviews/views.py
ajaxviews/static/require-ajax-views/dist/ajaxviews.js
ajaxviews/templates/ajaxviews/__ajax_base.html
ajaxviews/templates/ajaxviews/__modal_base.html
ajaxviews/templates/ajaxviews/_drag_drop.html
ajaxviews/templates/ajaxviews/_paginate.html
ajaxviews/templates/ajaxviews/_select_date_filter.html
ajaxviews/templates/ajaxviews/_select_multiple_filter.html
ajaxviews/templates/ajaxviews/_table_sort.html
ajaxviews/templates/ajaxviews/generic_form.html
django_ajax_views-0.0.2.dist-info/DESCRIPTION.rst
django_ajax_views-0.0.2.dist-info/METADATA
django_ajax_views-0.0.2.dist-info/RECORD
django_ajax_views-0.0.2.dist-info/WHEEL
django_ajax_views-0.0.2.dist-info/metadata.json
django_ajax_views-0.0.2.dist-info/top_level.txt
