Metadata-Version: 2.0
Name: django-ajax-views
Version: 0.0.2
Summary: Django class based views extension working together with js library require-ajax-views.
Home-page: https://github.com/Pyco7/django-ajax-views
Author: Emanuel Hafner
Author-email: dev@hafner.me
License: MIT
Keywords: django class based views javascript coffeescript ajax
Platform: UNKNOWN
Classifier: Development Status :: 4 - Beta
Classifier: Environment :: Web Environment
Classifier: Framework :: Django
Classifier: Intended Audience :: Developers
Classifier: License :: OSI Approved :: MIT License
Classifier: Operating System :: OS Independent
Classifier: Programming Language :: Python
Classifier: Programming Language :: Python :: 3
Classifier: Programming Language :: Python :: 3.3
Classifier: Programming Language :: Python :: 3.4
Classifier: Programming Language :: Python :: 3.5
Classifier: Topic :: Internet :: WWW/HTTP
Classifier: Topic :: Internet :: WWW/HTTP :: Dynamic Content
Classifier: Topic :: Software Development :: Libraries :: Python Modules
Requires-Dist: Django (>=1.9)
Requires-Dist: django-autocomplete-light (==2.3.3)
Requires-Dist: django-crispy-forms
Requires-Dist: django-extra-views
Requires-Dist: django-guardian
Requires-Dist: django-js-reverse
Requires-Dist: django-jsonify
Requires-Dist: django-require
